Metadata-Version: 2.4
Name: testeDIO
Version: 0.0.1
Summary: Teste modulo
Home-page: https://github.com/Gtropia/image-processing-package
Author: GabrielTropia
Author-email: gabriel_tropia@hotmail.com
Requires-Python: >=3.8
Dynamic: author
Dynamic: author-email
Dynamic: description-content-type
Dynamic: home-page
Dynamic: requires-python
Dynamic: summary
